README.md
setup.cfg
setup.py
cerebunit/__init__.py
cerebunit/fileManager.py
cerebunit/resultsManager.py
cerebunit.egg-info/PKG-INFO
cerebunit.egg-info/SOURCES.txt
cerebunit.egg-info/dependency_links.txt
cerebunit.egg-info/requires.txt
cerebunit.egg-info/top_level.txt
cerebunit/capabilities/__init__.py
cerebunit/capabilities/cells/__init__.py
cerebunit/capabilities/cells/measurements.py
cerebunit/capabilities/cells/response.py
cerebunit/statistics/__init__.py
cerebunit/statistics/data_conditions/__init__.py
cerebunit/statistics/data_conditions/forHTmeans.py
cerebunit/statistics/data_conditions/forHTproportions.py
cerebunit/statistics/hypothesis_testings/__init__.py
cerebunit/statistics/hypothesis_testings/aboutmeans.py
cerebunit/statistics/hypothesis_testings/aboutmedians.py
cerebunit/statistics/hypothesis_testings/aboutproportions.py
cerebunit/statistics/stat_scores/__init__.py
cerebunit/statistics/stat_scores/chi2GOFScore.py
cerebunit/statistics/stat_scores/chi2GOFScore_test_with_datasets.py
cerebunit/statistics/stat_scores/chi2Score.py
cerebunit/statistics/stat_scores/chi2Score_test_with_datasets.py
cerebunit/statistics/stat_scores/fisherExactScore.py
cerebunit/statistics/stat_scores/fisherExactScore_test_with_datasets.py
cerebunit/statistics/stat_scores/mcNemarScore.py
cerebunit/statistics/stat_scores/mcNemarScore_test_with_datasets.py
cerebunit/statistics/stat_scores/tScore.py
cerebunit/statistics/stat_scores/zPropScore.py
cerebunit/statistics/stat_scores/zPropScore_test_with_datasets.py
cerebunit/statistics/stat_scores/zScore.py
cerebunit/statistics/stat_scores/zSignScore.py
cerebunit/statistics/stat_scores/zSignScore_test_with_datasets.py
cerebunit/statistics/stat_scores/zTwoSampleRankSumScore.py
cerebunit/statistics/stat_scores/zTwoSampleRankSumScore_test_with_datasets.py
cerebunit/statistics/stat_scores/zWilcoxSignedRankScore.py
cerebunit/statistics/stat_scores/zWilcoxSignedRankScore_test_with_datasets.py
cerebunit/validation_tests/__init__.py
cerebunit/validation_tests/cells/__init__.py
cerebunit/validation_tests/cells/Granule/__init__.py
cerebunit/validation_tests/cells/Granule/test_for_restingVm.py
